pyanoled/Configuration.py
pyanoled/State.py
pyanoled/__init__.py
pyanoled/__main__.py
pyanoled/conf/app.conf
pyanoled/conf/default.conf
pyanoled/conf/system.conf
pyanoled/device/MIDIReader.py
pyanoled/device/__init__.py
pyanoled/event/EventQueue.py
pyanoled/event/Events.py
pyanoled/event/__init__.py
pyanoled/ui/ControlApp.py
pyanoled/ui/__init__.py
pyanoled/ui/displays/Display.py
pyanoled/ui/displays/LCD_1in44.py
pyanoled/ui/displays/LCD_Config.py
pyanoled/ui/displays/Waveshare144Display.py
pyanoled/ui/displays/__init__.py
pyanoled/ui/menus/ColorSchemeMenu.py
pyanoled/ui/menus/EffectMenu.py
pyanoled/ui/menus/MainMenu.py
pyanoled/ui/menus/Menu.py
pyanoled/ui/menus/SelectionItem.py
pyanoled/ui/menus/__init__.py
pyanoled/visualizer/LEDEngine.py
pyanoled/visualizer/__init__.py
pyanoled/visualizer/color_schemes/ChaosScheme.py
pyanoled/visualizer/color_schemes/DividedScheme.py
pyanoled/visualizer/color_schemes/KeyScheme.py
pyanoled/visualizer/color_schemes/MonoScheme.py
pyanoled/visualizer/color_schemes/Scheme.py
pyanoled/visualizer/color_schemes/__init__.py
pyanoled/visualizer/effects/Effect.py
pyanoled/visualizer/effects/FadeEffect.py
pyanoled/visualizer/effects/HoldEffect.py
pyanoled/visualizer/effects/LightEffect.py
pyanoled/visualizer/effects/__init__.py
pyanoled-1.0.0.dist-info/LICENSE
pyanoled-1.0.0.dist-info/METADATA
pyanoled-1.0.0.dist-info/WHEEL
pyanoled-1.0.0.dist-info/entry_points.txt
pyanoled-1.0.0.dist-info/top_level.txt
pyanoled-1.0.0.dist-info/RECORD
