Metadata-Version: 2.1
Name: pyanoled
Version: 1.0.0
Summary: Python Piano LED Visualizer
Home-page: https://github.com/ethanlu/pyanoled
Author: Ethan Lu
Author-email: fang.lu@gmail.com
License: MIT
Platform: UNKNOWN
Classifier: Development Status :: 5 - Production/Stable
Classifier: License :: OSI Approved :: MIT License
Classifier: Programming Language :: Python :: 3
Requires-Python: >3.6
Requires-Dist: cython
Requires-Dist: argparse
Requires-Dist: mido
Requires-Dist: numpy
Requires-Dist: Pillow
Requires-Dist: psutil
Requires-Dist: pyhocon
Requires-Dist: python-rtmidi
Requires-Dist: RPi.GPIO
Requires-Dist: rpi-ws281x
Requires-Dist: spidev
Requires-Dist: webcolors
Requires-Dist: wheel
